{"comments":[{"id":"65bddfe9c0d102007e29bc4b","parentId":null,"createdBy":{"fullName":"Stefan"},"website":"https://www.stefanjudis.com","html":"<p>Congrats on launching #mn&amp;n. 👏 Love reading these things!</p>\n","createdAt":1706942441852},{"id":"65bda64e7789b700aa32dc1e","parentId":null,"createdBy":{"fullName":"Michael Gale"},"website":"https://www.michaelgale.dev","html":"<p>Amazing work, Rach! I had a similar January where I am starting Feb feeling pretty positive.</p>\n<p>I compared my “closed fitness rings” on my Apple Watch this year to January of 2023 and its bananas how many more closed rings I’ve got this year. </p>\n<p>Anyway, good on you, hope the feet recover soon. </p>\n<p>-MG</p>\n","createdAt":1706927694442},{"id":"65c699347e4b02008095d313","parentId":null,"createdBy":{"fullName":"Kevin Spencer"},"website":"https://kevinspencer.org","html":"<p>I&#39;m somewhat still intrigued by the story of Elizabeth Holmes so will give The Dropout a go.</p>\n","createdAt":1707514164078},{"id":"65dc057c761a821c27f009b9","parentId":null,"createdBy":{"fullName":"j"},"website":"","html":"<p>have had a browse through your writing, congratulations on your chronicling! i hope to find similar success :)</p>\n","createdAt":1708918140782}]}